{
    "failed": false,
    "status": 200,
    "message": "Question Data fetched successfully",
    "data": {
        "question": {
            "questionFrontendId": "3204",
            "title": "Bitwise User Permissions Analysis",
            "titleSlug": "bitwise-user-permissions-analysis",
            "content": null,
            "isPaidOnly": true,
            "difficulty": "Medium",
            "likes": 4,
            "dislikes": 2,
            "similarQuestions": "[]",
            "topicTags": [
                {
                    "name": "Database",
                    "slug": "database"
                }
            ],
            "stats": "{\"totalAccepted\": \"371\", \"totalSubmission\": \"388\", \"totalAcceptedRaw\": 371, \"totalSubmissionRaw\": 388, \"acRate\": \"95.6%\"}",
            "hints": []
        },
        "similar": [],
        "hints": [],
        "relatedTopics": [
            {
                "name": "Database",
                "slug": "database"
            }
        ]
    }
}