{
  "status": 200,
  "message": "Question Data fetched successfully",
  "data": {
    "question": {
      "questionFrontendId": "250",
      "title": "Count Univalue Subtrees",
      "titleSlug": "count-univalue-subtrees",
      "content": null,
      "isPaidOnly": true,
      "difficulty": "Medium",
      "likes": 1175,
      "dislikes": 407,
      "similarQuestions": "[{\"title\": \"Subtree of Another Tree\", \"titleSlug\": \"subtree-of-another-tree\", \"difficulty\": \"Easy\", \"translatedTitle\": null}, {\"title\": \"Longest Univalue Path\", \"titleSlug\": \"longest-univalue-path\", \"difficulty\": \"Medium\", \"translatedTitle\": null}]",
      "topicTags": [
        {
          "name": "Tree",
          "slug": "tree"
        },
        {
          "name": "Depth-First Search",
          "slug": "depth-first-search"
        },
        {
          "name": "Binary Tree",
          "slug": "binary-tree"
        }
      ],
      "stats": "{\"totalAccepted\": \"148.2K\", \"totalSubmission\": \"263.8K\", \"totalAcceptedRaw\": 148162, \"totalSubmissionRaw\": 263765, \"acRate\": \"56.2%\"}",
      "hints": []
    },
    "similar": [
      {
        "difficulty": "Easy",
        "titleSlug": "subtree-of-another-tree",
        "title": "Subtree of Another Tree",
        "isPaidOnly": false
      },
      {
        "difficulty": "Medium",
        "titleSlug": "longest-univalue-path",
        "title": "Longest Univalue Path",
        "isPaidOnly": false
      }
    ],
    "hints": [],
    "relatedTopics": [
      {
        "name": "Tree",
        "slug": "tree"
      },
      {
        "name": "Depth-First Search",
        "slug": "depth-first-search"
      },
      {
        "name": "Binary Tree",
        "slug": "binary-tree"
      }
    ]
  }
}