{
  "failed": false,
  "status": 200,
  "message": "All Questions of Weekly-Contest-335",
  "data": [
    {
      "id": 3183,
      "question_id": 2645,
      "credit": 3,
      "title": "Pass the Pillow",
      "title_slug": "pass-the-pillow",
      "likes": 357,
      "dislikes": 15
    },
    {
      "id": 3184,
      "question_id": 2646,
      "credit": 4,
      "title": "Kth Largest Sum in a Binary Tree",
      "title_slug": "kth-largest-sum-in-a-binary-tree",
      "likes": 500,
      "dislikes": 15
    },
    {
      "id": 3185,
      "question_id": 2647,
      "credit": 5,
      "title": "Split the Array to Make Coprime Products",
      "title_slug": "split-the-array-to-make-coprime-products",
      "likes": 297,
      "dislikes": 110
    },
    {
      "id": 3186,
      "question_id": 2648,
      "credit": 6,
      "title": "Number of Ways to Earn Points",
      "title_slug": "number-of-ways-to-earn-points",
      "likes": 448,
      "dislikes": 9
    }
  ]
}